py_build_cmake/__init__.py
py_build_cmake/build.py
py_build_cmake/build_component.py
py_build_cmake/cli.py
py_build_cmake/help.py
py_build_cmake/commands/cmake.py
py_build_cmake/commands/cmd_runner.py
py_build_cmake/commands/env.py
py_build_cmake/commands/try_run.py
py_build_cmake/common/__init__.py
py_build_cmake/common/logformat.py
py_build_cmake/common/platform.py
py_build_cmake/common/util.py
py_build_cmake/config/__init__.py
py_build_cmake/config/cli_override.lark
py_build_cmake/config/cli_override.py
py_build_cmake/config/dynamic.py
py_build_cmake/config/environment.py
py_build_cmake/config/load.py
py_build_cmake/export/__init__.py
py_build_cmake/export/metadata.py
py_build_cmake/export/native_tags.py
py_build_cmake/export/sdist.py
py_build_cmake/export/tags.py
py_build_cmake/export/util.py
py_build_cmake/export/wheel.py
py_build_cmake/config/options/__init__.py
py_build_cmake/config/options/bool.py
py_build_cmake/config/options/cmake_opt.py
py_build_cmake/config/options/config_option.py
py_build_cmake/config/options/config_path.py
py_build_cmake/config/options/config_reference.py
py_build_cmake/config/options/default.py
py_build_cmake/config/options/dict.py
py_build_cmake/config/options/dir_pattern.py
py_build_cmake/config/options/enum.py
py_build_cmake/config/options/finalize.py
py_build_cmake/config/options/inherit.py
py_build_cmake/config/options/int.py
py_build_cmake/config/options/list.py
py_build_cmake/config/options/override.py
py_build_cmake/config/options/path.py
py_build_cmake/config/options/pyproject_options.py
py_build_cmake/config/options/string.py
py_build_cmake/config/options/value_reference.py
py_build_cmake/config/options/verify.py
py_build_cmake/config/quirks/__init__.py
py_build_cmake/config/quirks/macos.py
py_build_cmake/config/quirks/pyodide.py
py_build_cmake/config/quirks/windows.py
py_build_cmake/export/editable/__init__.py
py_build_cmake/export/editable/build_hook.py
py_build_cmake/export/editable/hook.py
py_build_cmake-0.5.0.dist-info/METADATA
py_build_cmake-0.5.0.dist-info/WHEEL
py_build_cmake-0.5.0.dist-info/entry_points.txt
py_build_cmake-0.5.0.dist-info/licenses/LICENSE
py_build_cmake-0.5.0.dist-info/RECORD
