Metadata-Version: 2.4
Name: py-build-cmake
Version: 0.5.0
Summary: Modern, PEP 517 compliant build backend for creating Python packages with
Keywords: pep517,cmake
Author-Email: Pieter P <pieter.p.dev@outlook.com>
License-Expression: MIT
License-File: LICENSE
Classifier: Development Status :: 5 - Production/Stable
Classifier: Topic :: System :: Archiving :: Packaging
Classifier: Topic :: System :: Software Distribution
Classifier: Programming Language :: Python :: 3
Classifier: Programming Language :: Python :: 3.7
Classifier: Programming Language :: Python :: 3.8
Classifier: Programming Language :: Python :: 3.9
Classifier: Programming Language :: Python :: 3.10
Classifier: Programming Language :: Python :: 3.11
Classifier: Programming Language :: Python :: 3.12
Classifier: Programming Language :: Python :: 3.13
Classifier: Operating System :: POSIX :: Linux
Classifier: Operating System :: Microsoft :: Windows
Classifier: Operating System :: MacOS
Project-URL: Source, https://github.com/tttapa/py-build-cmake
Project-URL: Documentation, https://tttapa.github.io/py-build-cmake
Project-URL: Tracker, https://github.com/tttapa/py-build-cmake/issues
Requires-Python: >=3.7
Requires-Dist: distlib~=0.4.0
Requires-Dist: packaging>=23.2
Requires-Dist: pyproject-metadata~=0.9.1
Requires-Dist: tomli<3,>=1.2.3; python_version < "3.11"
Requires-Dist: lark<2,>=1.1.9
Requires-Dist: click<9,>=8.1.3
Provides-Extra: test
Requires-Dist: nox<2026,>=2023.4.22; extra == "test"
Requires-Dist: jinja2~=3.1.2; extra == "test"
Provides-Extra: docs
Requires-Dist: sphinx==8.2.3; extra == "docs"
Requires-Dist: sphinx-book-theme==1.1.4; extra == "docs"
Requires-Dist: sphinx_design==0.6.1; extra == "docs"
Requires-Dist: myst-parser==4.0.1; extra == "docs"
